chapter_05/tut5.v

`timescale	1ns / 1ns
`default_nettype none


/*Produced by NSL Core(version=20250428), IP ARCH, Inc. Wed Apr 15 16:48:03 2026
 Licensed to :EVALUATION USER*/

// synthesis translate_off
// synopsys translate_off
/*
 DO NOT USE ANY PART OF THIS FILE FOR COMMERCIAL PRODUCTS. 
*/

module tut5 ( p_reset , m_clock );
  input p_reset, m_clock;
  wire p_reset, m_clock;
  reg [4:0] count;
  wire [4:0] x;
  wire [4:0] y;
  wire _net_0;
  wire _net_3;

   assign  x = (_net_3)? ((_net_3)?(count+5'b00001):5'b0):5'bx;
   assign  y = (_net_3)? ((_net_3)?(x+5'b00001):5'b0):5'bx;
   assign  _net_0 = (count >= 5'b01010);
always @(posedge m_clock)
  begin
    if(_net_0)
    begin
    $display("End");
    end
  end
always @(posedge m_clock)
  begin
    if(_net_0)
    begin
    $finish;
    end
  end
   assign  _net_3 = (count < 5'b01010);
always @(posedge m_clock)
  begin
    if(_net_3)
    begin
    $display("x=%d,y=%d,count=%d",x,y,count);
    end
  end
always @(posedge m_clock or posedge p_reset)
  begin
if (p_reset)
     count <= 5'b00000;
else if (_net_3)
      count <= x;
end
endmodule

// synthesis translate_on
// synopsys translate_on

/*Produced by NSL Core(version=20250428), IP ARCH, Inc. Wed Apr 15 16:48:03 2026
 Licensed to :EVALUATION USER*/

/*Produced by NSL Core(version=20250428), IP ARCH, Inc. Wed Apr 15 16:48:03 2026
 Licensed to :EVALUATION USER*/

//synthesis translate_off
/*
 DO NOT USE ANY PART OF THIS FILE FOR COMMERCIAL PRODUCTS. 
*/
module tb;
	parameter tCYC=2;
	parameter tPD=(tCYC/10);

	reg p_reset;
	reg m_clock;

	tut5 tut5_instance(
		.p_reset(p_reset),
		.m_clock(m_clock)
	);

	initial forever #(tCYC/2) m_clock = ~m_clock;

	initial begin
		$dumpfile("tut5.vcd");
		$dumpvars(0,tut5_instance);
	end

	initial begin
		#(tPD)
			p_reset = 1;
			m_clock = 0;
		#(tCYC)
			p_reset = 0;
	end

endmodule

//synthesis translate_on

chapter_05/tut5.vcd
$date
	Wed Apr 15 16:49:40 2026
$end
$version
	Icarus Verilog
$end
$timescale
	1ns
$end
$scope module tb $end
$scope module tut5_instance $end
$var wire 1 ! m_clock $end
$var wire 1 " p_reset $end
$var wire 5 # y [4:0] $end
$var wire 5 $ x [4:0] $end
$var wire 1 % _net_3 $end
$var wire 1 & _net_0 $end
$var reg 5 ' count [4:0] $end
$upscope $end
$upscope $end
$enddefinitions $end
#0
$dumpvars
b0 '
0&
1%
b1 $
b10 #
1"
0!
$end
#1
1!
#2
0!
0"
#3
b11 #
b10 $
b1 '
1!
#4
0!
#5
b100 #
b11 $
b10 '
1!
#6
0!
#7
b101 #
b100 $
b11 '
1!
#8
0!
#9
b110 #
b101 $
b100 '
1!
#10
0!
#11
b111 #
b110 $
b101 '
1!
#12
0!
#13
b1000 #
b111 $
b110 '
1!
#14
0!
#15
b1001 #
b1000 $
b111 '
1!
#16
0!
#17
b1010 #
b1001 $
b1000 '
1!
#18
0!
#19
b1011 #
b1010 $
b1001 '
1!
#20
0!
#21
bx #
bx $
1&
0%
b1010 '
1!
