chapter_10/tut10.v

`timescale	1ns / 1ns
`default_nettype none


/*Produced by NSL Core(version=20250428), IP ARCH, Inc. Fri Apr 17 20:59:02 2026
 Licensed to :EVALUATION USER*/
/*
 DO NOT USE ANY PART OF THIS FILE FOR COMMERCIAL PRODUCTS. 
*/

module divu_10_8 ( p_reset , m_clock , A , B , Q , R , divu_do , divu_done , divu_error );
  input p_reset, m_clock;
  wire p_reset, m_clock;
  input [9:0] A;
  wire [9:0] A;
  input [7:0] B;
  wire [7:0] B;
  output [9:0] Q;
  wire [9:0] Q;
  output [7:0] R;
  wire [7:0] R;
  input divu_do;
  wire divu_do;
  output divu_done;
  wire divu_done;
  output divu_error;
  wire divu_error;
  reg [7:0] QB;
  reg [17:0] QQ;
  wire [10:0] sub_i1;
  wire [9:0] sub_i2;
  wire minus;
  wire sub;
  wire [10:0] sub_o;
  reg [7:0] bitcount;
  wire [7:0] _net_2;
  wire _net_3;
  reg _reg_4;
  reg _reg_5;
  reg _reg_6;
  wire _net_7;
  wire _reg_5_goto;
  wire _reg_4_goin;
  wire _net_8;
  wire _reg_5_goin;
  wire [7:0] _net_9;
  wire [19:0] _net_10;
  wire [35:0] _net_11;
  wire [17:0] _net_12;
  wire [21:0] _net_13;
  wire [10:0] _net_14;
  wire _net_15;

   assign  sub_i1 = 
// synthesis translate_off
// synopsys translate_off
((_reg_5&(~_net_7)))? 
// synthesis translate_on
// synopsys translate_on
(((_reg_5&(~_net_7)))?(QQ[17:7]):11'b0)
// synthesis translate_off
// synopsys translate_off
:11'bx
// synthesis translate_on
// synopsys translate_on
;
   assign  sub_i2 = 
// synthesis translate_off
// synopsys translate_off
((_reg_5&(~_net_7)))? 
// synthesis translate_on
// synopsys translate_on
(((_reg_5&(~_net_7)))?(_net_10[17:8]):10'b0)
// synthesis translate_off
// synopsys translate_off
:10'bx
// synthesis translate_on
// synopsys translate_on
;
   assign  minus = 
// synthesis translate_off
// synopsys translate_off
(sub)? 
// synthesis translate_on
// synopsys translate_on
((sub)?(sub_o[10]):1'b0)
// synthesis translate_off
// synopsys translate_off
:1'bx
// synthesis translate_on
// synopsys translate_on
;

// synthesis translate_off
// synopsys translate_off
always @(posedge sub)
  begin
#1 if (sub===1'bx)
 begin
$display("Warning: control hazard(divu_10_8:sub) at %d",$time);
 end
#1 if ((((_reg_5&(~_net_7)))===1'bx) || (1'b1)===1'bx) $display("hazard ((_reg_5&(~_net_7)) || 1'b1) line 37 at %d\n",$time);
 end

// synthesis translate_on
// synopsys translate_on
   assign  sub = (_reg_5&(~_net_7));
   assign  sub_o = 
// synthesis translate_off
// synopsys translate_off
(sub)? 
// synthesis translate_on
// synopsys translate_on
((sub)?(({sub_i1})-({1'b0,sub_i2})):11'b0)
// synthesis translate_off
// synopsys translate_off
:11'bx
// synthesis translate_on
// synopsys translate_on
;
   assign  _net_2 = 
// synthesis translate_off
// synopsys translate_off
((_reg_5&(~_net_7)))? 
// synthesis translate_on
// synopsys translate_on
(((_reg_5&(~_net_7)))?(bitcount+8'b00000001):8'b0)
// synthesis translate_off
// synopsys translate_off
:8'bx
// synthesis translate_on
// synopsys translate_on
;
   assign  _net_3 = 
// synthesis translate_off
// synopsys translate_off
(divu_do)? 
// synthesis translate_on
// synopsys translate_on
((divu_do)?(B==8'b00000000):1'b0)
// synthesis translate_off
// synopsys translate_off
:1'bx
// synthesis translate_on
// synopsys translate_on
;
   assign  _net_7 = 
// synthesis translate_off
// synopsys translate_off
(_reg_5)? 
// synthesis translate_on
// synopsys translate_on
((_reg_5)?(~(bitcount < 8'b00001010)):1'b0)
// synthesis translate_off
// synopsys translate_off
:1'bx
// synthesis translate_on
// synopsys translate_on
;

// synthesis translate_off
// synopsys translate_off
always @(posedge _reg_5_goto)
  begin
#1 if (_reg_5_goto===1'bx)
 begin
$display("Warning: control hazard(divu_10_8:_reg_5_goto) at %d",$time);
 end
#1 if (((((_reg_5&(~_net_7))&_net_8))===1'bx) || (1'b1)===1'bx) $display("hazard (((_reg_5&(~_net_7))&_net_8) || 1'b1) line 43 at %d\n",$time);
#1 if ((((_reg_5&_net_7))===1'bx) || (1'b1)===1'bx) $display("hazard ((_reg_5&_net_7) || 1'b1) line 43 at %d\n",$time);
 end

// synthesis translate_on
// synopsys translate_on
   assign  _reg_5_goto = ((_reg_5&(~_net_7))&_net_8)|
    (_reg_5&_net_7);

// synthesis translate_off
// synopsys translate_off
always @(posedge _reg_4_goin)
  begin
#1 if (_reg_4_goin===1'bx)
 begin
$display("Warning: control hazard(divu_10_8:_reg_4_goin) at %d",$time);
 end
#1 if ((((_reg_5&_net_7))===1'bx) || (1'b1)===1'bx) $display("hazard ((_reg_5&_net_7) || 1'b1) line 43 at %d\n",$time);
 end

// synthesis translate_on
// synopsys translate_on
   assign  _reg_4_goin = (_reg_5&_net_7);
   assign  _net_8 = 
// synthesis translate_off
// synopsys translate_off
((_reg_5&(~_net_7)))? 
// synthesis translate_on
// synopsys translate_on
(((_reg_5&(~_net_7)))?(_net_2 < 8'b00001010):1'b0)
// synthesis translate_off
// synopsys translate_off
:1'bx
// synthesis translate_on
// synopsys translate_on
;

// synthesis translate_off
// synopsys translate_off
always @(posedge _reg_5_goin)
  begin
#1 if (_reg_5_goin===1'bx)
 begin
$display("Warning: control hazard(divu_10_8:_reg_5_goin) at %d",$time);
 end
#1 if (((((_reg_5&(~_net_7))&_net_8))===1'bx) || (1'b1)===1'bx) $display("hazard (((_reg_5&(~_net_7))&_net_8) || 1'b1) line 43 at %d\n",$time);
 end

// synthesis translate_on
// synopsys translate_on
   assign  _reg_5_goin = ((_reg_5&(~_net_7))&_net_8);
   assign  _net_9 = QB;
   assign  _net_10 = ({({2'b00,_net_9}),10'b0000000000});
   assign  _net_11 = ({QQ,18'b000000000000000000});
   assign  _net_12 = ({(QQ[8:0]),9'b000000000});
   assign  _net_13 = ({sub_o,11'b00000000000});
   assign  _net_14 = (_net_13[20:10]);
   assign  _net_15 = 1'b1;
   assign  Q = 
// synthesis translate_off
// synopsys translate_off
(_reg_4)? 
// synthesis translate_on
// synopsys translate_on
((_reg_4)?(QQ[9:0]):10'b0)
// synthesis translate_off
// synopsys translate_off
:10'bx
// synthesis translate_on
// synopsys translate_on
;
   assign  R = 
// synthesis translate_off
// synopsys translate_off
(_reg_4)? 
// synthesis translate_on
// synopsys translate_on
((_reg_4)?(QQ[17:10]):8'b0)
// synthesis translate_off
// synopsys translate_off
:8'bx
// synthesis translate_on
// synopsys translate_on
;

// synthesis translate_off
// synopsys translate_off
always @(posedge divu_done)
  begin
#1 if (divu_done===1'bx)
 begin
$display("Warning: control hazard(divu_10_8:divu_done) at %d",$time);
 end
#1 if (((_reg_4)===1'bx) || (1'b1)===1'bx) $display("hazard (_reg_4 || 1'b1) line 45 at %d\n",$time);
 end

// synthesis translate_on
// synopsys translate_on
   assign  divu_done = _reg_4;

// synthesis translate_off
// synopsys translate_off
always @(posedge divu_error)
  begin
#1 if (divu_error===1'bx)
 begin
$display("Warning: control hazard(divu_10_8:divu_error) at %d",$time);
 end
#1 if ((((divu_do&_net_3))===1'bx) || (1'b1)===1'bx) $display("hazard ((divu_do&_net_3) || 1'b1) line 29 at %d\n",$time);
 end

// synthesis translate_on
// synopsys translate_on
   assign  divu_error = (divu_do&_net_3);
always @(posedge m_clock)
  begin
if (((divu_do&(~_net_3))|_reg_6))
      QB <= B;
end
always @(posedge m_clock)
  begin

// synthesis translate_off
// synopsys translate_off
if (((((divu_do&(~_net_3))|_reg_6)&((_reg_5&(~_net_7))&(~(minus != 1'b0))))|((((divu_do&(~_net_3))|_reg_6)|((_reg_5&(~_net_7))&(~(minus != 1'b0))))&((_reg_5&(~_net_7))&(minus != 1'b0)))))   QQ <= 18'bx; 
  else 
// synthesis translate_on
// synopsys translate_on
if (((divu_do&(~_net_3))|_reg_6))
      QQ <= ({8'b00000000,A});
else if (((_reg_5&(~_net_7))&(~(minus != 1'b0))))
      QQ <= (({(_net_14[10:2]),(_net_12[16:8])})|({17'b00000000000000000,_net_15}));
else if (((_reg_5&(~_net_7))&(minus != 1'b0)))
      QQ <= (_net_11[34:17]);
end

// synthesis translate_off
// synopsys translate_off
always @(posedge m_clock)
  begin
if ((((((divu_do&(~_net_3))|_reg_6)|((_reg_5&(~_net_7))&(~(minus != 1'b0))))|((_reg_5&(~_net_7))&(minus != 1'b0)))==1'b1) ||
 (((((divu_do&(~_net_3))|_reg_6)|((_reg_5&(~_net_7))&(~(minus != 1'b0))))|((_reg_5&(~_net_7))&(minus != 1'b0)))==1'b0) ) begin
 if (((((divu_do&(~_net_3))|_reg_6)&((_reg_5&(~_net_7))&(~(minus != 1'b0))))|((((divu_do&(~_net_3))|_reg_6)|((_reg_5&(~_net_7))&(~(minus != 1'b0))))&((_reg_5&(~_net_7))&(minus != 1'b0)))))
 begin $display("Warning: assign collision(divu_10_8:QQ) at %d",$time);

  end
 end
 else 
 $display("Warning: register set hazard(divu_10_8:QQ) at %d",$time);

  end

// synthesis translate_on
// synopsys translate_on
always @(posedge m_clock)
  begin

// synthesis translate_off
// synopsys translate_off
if ((((divu_do&(~_net_3))|_reg_6)&(_reg_5&(~_net_7))))   bitcount <= 8'bx; 
  else 
// synthesis translate_on
// synopsys translate_on
if (((divu_do&(~_net_3))|_reg_6))
      bitcount <= 8'b00000000;
else if ((_reg_5&(~_net_7)))
      bitcount <= _net_2;
end

// synthesis translate_off
// synopsys translate_off
always @(posedge m_clock)
  begin
if (((((divu_do&(~_net_3))|_reg_6)|(_reg_5&(~_net_7)))==1'b1) ||
 ((((divu_do&(~_net_3))|_reg_6)|(_reg_5&(~_net_7)))==1'b0) ) begin
 if ((((divu_do&(~_net_3))|_reg_6)&(_reg_5&(~_net_7))))
 begin $display("Warning: assign collision(divu_10_8:bitcount) at %d",$time);

  end
 end
 else 
 $display("Warning: register set hazard(divu_10_8:bitcount) at %d",$time);

  end

// synthesis translate_on
// synopsys translate_on
always @(posedge m_clock or posedge p_reset)
  begin
if (p_reset)
     _reg_4 <= 1'b0;
else if (((_reg_5&_net_7)|(_reg_4|_reg_5)))
      _reg_4 <= ((_reg_5&_net_7)|(_reg_5&(~_reg_5_goto)));
end
always @(posedge m_clock or posedge p_reset)
  begin
if (p_reset)
     _reg_5 <= 1'b0;
else if (((((_reg_5&(~_net_7))&_net_8)|(divu_do&(~_net_3)))|(_reg_5|_reg_6)))
      _reg_5 <= ((((_reg_5&(~_net_7))&_net_8)|_reg_6)|(divu_do&(~_net_3)));
end
always @(posedge m_clock or posedge p_reset)
  begin
if (p_reset)
     _reg_6 <= 1'b0;
else if (_reg_6)
      _reg_6 <= 1'b0;
end
endmodule

/*Produced by NSL Core(version=20250428), IP ARCH, Inc. Fri Apr 17 20:59:02 2026
 Licensed to :EVALUATION USER*/

/*Produced by NSL Core(version=20250428), IP ARCH, Inc. Fri Apr 17 20:59:02 2026
 Licensed to :EVALUATION USER*/

// synthesis translate_off
// synopsys translate_off
/*
 DO NOT USE ANY PART OF THIS FILE FOR COMMERCIAL PRODUCTS. 
*/

module tut10 ( p_reset , m_clock );
  input p_reset, m_clock;
  wire p_reset, m_clock;
  reg [9:0] a;
  reg [7:0] b;
  wire go;
  reg [15:0] count;
  reg [31:0] _reg_16;
  reg [31:0] _reg_17;
  wire [9:0] _divid_A;
  wire [7:0] _divid_B;
  wire [9:0] _divid_Q;
  wire [7:0] _divid_R;
  wire _divid_divu_do;
  wire _divid_divu_done;
  wire _divid_divu_error;
  wire _divid_p_reset;
  wire _divid_m_clock;
  wire _net_18;
  reg _reg_21;
  reg _reg_22;
  reg _reg_23;
  reg _reg_24;
  wire _net_26;
  wire _reg_22_goto;
  wire _reg_22_goin;
  wire [31:0] _net_29;
  wire [31:0] _net_30;
divu_10_8 divid (.m_clock(m_clock), .p_reset( p_reset), .divu_error(_divid_divu_error), .divu_done(_divid_divu_done), .divu_do(_divid_divu_do), .Q(_divid_Q), .R(_divid_R), .A(_divid_A), .B(_divid_B));

always @(posedge go)
  begin
#1 if (go===1'bx)
 begin
$display("Warning: control hazard(tut10:go) at %d",$time);
 end
#1 if (((_net_18)===1'bx) || (1'b1)===1'bx) $display("hazard (_net_18 || 1'b1) line 61 at %d\n",$time);
 end
   assign  go = _net_18;
   assign  _divid_A = (_reg_23)? ((_reg_23)?a:10'b0):10'bx;
   assign  _divid_B = (_reg_23)? ((_reg_23)?b:8'b0):8'bx;
always @(posedge _divid_divu_do)
  begin
#1 if (_divid_divu_do===1'bx)
 begin
$display("Warning: control hazard(tut10:_divid_divu_do) at %d",$time);
 end
#1 if (((_reg_23)===1'bx) || (1'b1)===1'bx) $display("hazard (_reg_23 || 1'b1) line 75 at %d\n",$time);
 end
   assign  _divid_divu_do = _reg_23;
   assign  _divid_p_reset = p_reset;
   assign  _divid_m_clock = m_clock;
   assign  _net_18 = (count==16'b0000000000001010);
always @(posedge m_clock) // there are several "always @(posedge m_clock)" blocks in this file.
  begin                   // It is because we want to divide the circuit as a function. 
    if((_divid_divu_error != 1'b0))   // If we put all the statements in one "always @(posedge m_clock)" block, 
    begin                             // the circuit will be very complicated and it becomes difficult to optimize the circuit. // YOSHII memo
    $display("divid error");
    end
  end
always @(posedge m_clock)
  begin
    if((_divid_divu_error != 1'b0))
    begin
    $finish;
    end
  end
always @(posedge m_clock)
  begin
    if(_reg_21)
    begin
    $finish;
    end
  end
   assign  _net_26 = (_reg_22)? ((_reg_22)?(~_divid_divu_done):1'b0):1'bx;
always @(posedge _reg_22_goto)
  begin
#1 if (_reg_22_goto===1'bx)
 begin
$display("Warning: control hazard(tut10:_reg_22_goto) at %d",$time);
 end
#1 if ((((_reg_22&_net_26))===1'bx) || (1'b1)===1'bx) $display("hazard ((_reg_22&_net_26) || 1'b1) line 80 at %d\n",$time);
 end
   assign  _reg_22_goto = (_reg_22&_net_26);
always @(posedge _reg_22_goin)
  begin
#1 if (_reg_22_goin===1'bx)
 begin
$display("Warning: control hazard(tut10:_reg_22_goin) at %d",$time);
 end
#1 if ((((_reg_22&_net_26))===1'bx) || (1'b1)===1'bx) $display("hazard ((_reg_22&_net_26) || 1'b1) line 80 at %d\n",$time);
 end
   assign  _reg_22_goin = (_reg_22&_net_26);
always @(posedge m_clock)
  begin
    if((_reg_22&(~_net_26)))
    begin
    $display("result = %d : %d",_divid_Q,_divid_R);
    end
  end
always @(posedge m_clock)
  begin
    if(_reg_23)
    begin
    $display("start %d/%d",a,b);
    end
  end
   assign  _net_29 = _reg_16;
   assign  _net_30 = _reg_17;
always @(posedge m_clock)
  begin
if ((go|_reg_24))
      a <= (_net_29[9:0]);
end
always @(posedge m_clock)
  begin
if ((go|_reg_24))
      b <= (_net_30[7:0]);
end
always @(posedge m_clock or posedge p_reset)
  begin
if (p_reset)
     count <= 16'b0000000000000000;
else   count <= (count+16'b0000000000000001);
end
always @(posedge m_clock)
  begin
  _reg_16 <= ($random);
end
always @(posedge m_clock)
  begin
  _reg_17 <= ($random);
end
always @(posedge m_clock or posedge p_reset)
  begin
if (p_reset)
     _reg_21 <= 1'b0;
else if ((_reg_21|_reg_22))
      _reg_21 <= (_reg_22&(~_reg_22_goto));
end
always @(posedge m_clock or posedge p_reset)
  begin
if (p_reset)
     _reg_22 <= 1'b0;
else if (((_reg_22&_net_26)|(_reg_22|_reg_23)))
      _reg_22 <= ((_reg_22&_net_26)|_reg_23);
end
always @(posedge m_clock or posedge p_reset)
  begin
if (p_reset)
     _reg_23 <= 1'b0;
else if ((go|(_reg_23|_reg_24)))
      _reg_23 <= (_reg_24|go);
end
always @(posedge m_clock or posedge p_reset)
  begin
if (p_reset)
     _reg_24 <= 1'b0;
else if (_reg_24)
      _reg_24 <= 1'b0;
end
endmodule

// synthesis translate_on
// synopsys translate_on

/*Produced by NSL Core(version=20250428), IP ARCH, Inc. Fri Apr 17 20:59:02 2026
 Licensed to :EVALUATION USER*/

/*Produced by NSL Core(version=20250428), IP ARCH, Inc. Fri Apr 17 20:59:02 2026
 Licensed to :EVALUATION USER*/

//synthesis translate_off
/*
 DO NOT USE ANY PART OF THIS FILE FOR COMMERCIAL PRODUCTS. 
*/
module tb;
	parameter tCYC=2;
	parameter tPD=(tCYC/10);

	reg p_reset;
	reg m_clock;

	tut10 tut10_instance(
		.p_reset(p_reset),
		.m_clock(m_clock)
	);

	initial forever #(tCYC/2) m_clock = ~m_clock;

	initial begin
		$dumpfile("tut10.vcd");
		$dumpvars(0,tut10_instance);
	end

	initial begin
		#(tPD)
			p_reset = 1;
			m_clock = 0;
		#(tCYC)
			p_reset = 0;
	end

endmodule

//synthesis translate_on

chapter_10/tut10.vcd
$date
	Fri Apr 17 20:59:06 2026
$end
$version
	Icarus Verilog
$end
$timescale
	1ns
$end
$scope module tb $end
$scope module tut10_instance $end
$var wire 1 ! _divid_divu_do $end
$var wire 1 " _divid_m_clock $end
$var wire 1 # _divid_p_reset $end
$var wire 32 $ _net_29 [31:0] $end
$var wire 32 % _net_30 [31:0] $end
$var wire 1 & _reg_22_goin $end
$var wire 1 ' _reg_22_goto $end
$var wire 1 ( go $end
$var wire 1 ) m_clock $end
$var wire 1 * p_reset $end
$var wire 1 + _net_26 $end
$var wire 1 , _net_18 $end
$var wire 1 - _divid_divu_error $end
$var wire 1 . _divid_divu_done $end
$var wire 8 / _divid_R [7:0] $end
$var wire 10 0 _divid_Q [9:0] $end
$var wire 8 1 _divid_B [7:0] $end
$var wire 10 2 _divid_A [9:0] $end
$var reg 32 3 _reg_16 [31:0] $end
$var reg 32 4 _reg_17 [31:0] $end
$var reg 1 5 _reg_21 $end
$var reg 1 6 _reg_22 $end
$var reg 1 7 _reg_23 $end
$var reg 1 8 _reg_24 $end
$var reg 10 9 a [9:0] $end
$var reg 8 : b [7:0] $end
$var reg 16 ; count [15:0] $end
$scope module divid $end
$var wire 10 < A [9:0] $end
$var wire 8 = B [7:0] $end
$var wire 1 > _net_15 $end
$var wire 8 ? _net_9 [7:0] $end
$var wire 1 @ _reg_4_goin $end
$var wire 1 A _reg_5_goin $end
$var wire 1 B _reg_5_goto $end
$var wire 1 ! divu_do $end
$var wire 1 . divu_done $end
$var wire 1 - divu_error $end
$var wire 1 ) m_clock $end
$var wire 1 * p_reset $end
$var wire 1 C sub $end
$var wire 11 D sub_o [10:0] $end
$var wire 10 E sub_i2 [9:0] $end
$var wire 11 F sub_i1 [10:0] $end
$var wire 1 G minus $end
$var wire 1 H _net_8 $end
$var wire 1 I _net_7 $end
$var wire 1 J _net_3 $end
$var wire 8 K _net_2 [7:0] $end
$var wire 11 L _net_14 [10:0] $end
$var wire 22 M _net_13 [21:0] $end
$var wire 18 N _net_12 [17:0] $end
$var wire 36 O _net_11 [35:0] $end
$var wire 20 P _net_10 [19:0] $end
$var wire 8 Q R [7:0] $end
$var wire 10 R Q [9:0] $end
$var reg 8 S QB [7:0] $end
$var reg 18 T QQ [17:0] $end
$var reg 1 U _reg_4 $end
$var reg 1 V _reg_5 $end
$var reg 1 W _reg_6 $end
$var reg 8 X bitcount [7:0] $end
$upscope $end
$upscope $end
$upscope $end
$enddefinitions $end
#0
$dumpvars
bx X
0W
0V
0U
bx T
bx S
bx R
bx Q
b0xxxxxxxx0000000000 P
bx000000000000000000 O
bx000000000 N
bx00000000000 M
bx0 L
bx K
xJ
xI
xH
xG
bx F
bx E
bx D
0C
0B
0A
0@
bx ?
1>
bx =
bx <
b0 ;
bx :
bx 9
08
07
06
05
bx 4
bx 3
bx 2
bx 1
bx 0
bx /
0.
0-
0,
x+
1*
0)
0(
0'
0&
bx %
bx $
1#
0"
0!
$end
#1
b11000000100010010101111010000001 $
b11000000100010010101111010000001 3
b10010000101010011010100100100 %
b10010000101010011010100100100 4
1"
1)
#2
0"
0)
0#
0*
#3
b1 ;
b10110001111100000101011001100011 %
b10110001111100000101011001100011 4
b10000100100001001101011000001001 $
b10000100100001001101011000001001 3
1"
1)
#4
0"
0)
#5
b10 ;
b1000110110111111001100110001101 $
b1000110110111111001100110001101 3
b110101110010111101100001101 %
b110101110010111101100001101 4
1"
1)
#6
0"
0)
#7
b11 ;
b10001001001101110101001000010010 %
b10001001001101110101001000010010 4
b10110010110000101000010001100101 $
b10110010110000101000010001100101 3
1"
1)
#8
0"
0)
#9
b100 ;
b110110101111100110100001101 $
b110110101111100110100001101 3
b111100111110001100000001 %
b111100111110001100000001 4
1"
1)
#10
0"
0)
#11
b101 ;
b11110100011011100110100111101 %
b11110100011011100110100111101 4
b111011001000111111000101110110 $
b111011001000111111000101110110 3
1"
1)
#12
0"
0)
#13
b110 ;
b1000110001011011111011110001100 $
b1000110001011011111011110001100 3
b1110110110101000101011111101101 %
b1110110110101000101011111101101 4
1"
1)
#14
0"
0)
#15
b111 ;
b11100011001101110010010011000110 %
b11100011001101110010010011000110 4
b1111100111111011110100111111001 $
b1111100111111011110100111111001 3
1"
1)
#16
0"
0)
#17
b1000 ;
b11010101000100111101001010101010 $
b11010101000100111101001010101010 3
b11100010111101111000010011000101 %
b11100010111101111000010011000101 4
1"
1)
#18
0"
0)
#19
b1001 ;
b10111011110100100111001001110111 %
b10111011110100100111001001110111 4
b1110010101011111111011111100101 $
b1110010101011111111011111100101 3
1"
1)
#20
0"
0)
#21
1(
1,
b1010 ;
b1000111111011001101101110001111 $
b1000111111011001101101110001111 3
b10001001001100101101011000010010 %
b10001001001100101101011000010010 4
1"
1)
#22
0"
0)
#23
0-
b1110001111 2
b1110001111 <
b10010 1
b10010 =
0J
0(
0,
b1011 ;
1!
17
b11100111011101101001011011001110 %
b11100111011101101001011011001110 4
b1111001001100000110100111110010 $
b1111001001100000110100111110010 3
b10010 :
b1110001111 9
1"
1)
#24
0"
0)
#25
1G
b11101111110 L
1H
b1111011111100000000000 M
b11110111111 D
b1 K
b1001000 E
b111 F
1A
1B
bx 2
bx <
bx 1
bx =
xJ
1+
1&
1'
0I
0@
1C
b110001111000000000 N
0!
07
16
b1100 ;
1V
b100100000000000 P
b10010 ?
b10010 S
b1110001111000000000000000000 O
b1110001111 T
b0 X
b11100010110010100100111011000101 $
b11100010110010100100111011000101 3
b11110100000000000111101011101000 %
b11110100000000000111101011101000 4
1"
1)
#26
0"
0)
#27
b11110001100 L
b1111100011000000000000 M
b11111000110 D
b1110 F
b10 K
b100011110000000000 N
b1101 ;
b11011110100011100010100010111101 %
b11011110100011100010100010111101 4
b101110010110000100100101011100 $
b101110010110000100100101011100 3
b1 X
b11100011110000000000000000000 O
b11100011110 T
1"
1)
#28
0"
0)
#29
b11110101000 L
b1111101010000000000000 M
b11111010100 D
b11100 F
b11 K
b111100000000000 N
b1110 ;
b111000111100000000000000000000 O
b111000111100 T
b10 X
b10110010101001110010011001100101 $
b10110010101001110010011001100101 3
b10010110101010110101100000101101 %
b10010110101010110101100000101101 4
1"
1)
#30
0"
0)
#31
b11111100000 L
b1111111000000000000000 M
b11111110000 D
b111000 F
b100 K
b1111000000000000 N
b1111 ;
b101011100111000011100001010 %
b101011100111000011100001010 4
b10110001111011110110001001100011 $
b10110001111011110110001001100011 3
b11 X
b1110001111000000000000000000000 O
b1110001111000 T
1"
1)
#32
0"
0)
#33
0G
b1010010 L
b10100100000000000 M
b101001 D
b1110001 F
b101 K
b11110000000000000 N
b10000 ;
b11100011110000000000000000000000 O
b11100011110000 T
b100 X
b10000011001000010000100100000 $
b10000011001000010000100100000 3
b11000000001110110010001010000000 %
b11000000001110110010001010000000 4
1"
1)
#34
0"
0)
#35
b10110 L
b101100000000000 M
b1011 D
b1010011 F
b110 K
b111100001000000000 N
b10001 ;
b11001110110011001100110010011101 %
b11001110110011001100110010011101 4
b1010101011110000100010110101010 $
b1010101011110000100010110101010 3
b101 X
b10100111100001000000000000000000 O
b10100111100001 T
1"
1)
#36
0"
0)
#37
1G
b11110011110 L
b1111100111100000000000 M
b11111001111 D
b10111 F
b111 K
b111000011000000000 N
b10010 ;
b101111000011000000000000000000 O
b101111000011 T
b110 X
b10001001100000111011100000010011 $
b10001001100000111011100000010011 3
b11001011001000000011111010010110 %
b11001011001000000011111010010110 4
1"
1)
#38
0"
0)
#39
b11111001110 L
b1111110011100000000000 M
b11111100111 D
b101111 F
b1000 K
b110000110000000000 N
b10011 ;
b10101001101001111101011001010011 %
b10101001101001111101011001010011 4
b10000110101111000011100000001101 $
b10000110101111000011100000001101 3
b111 X
b1011110000110000000000000000000 O
b1011110000110 T
1"
1)
#40
0"
0)
#41
0G
b101100 L
b1011000000000000 M
b10110 D
b1011110 F
b1001 K
b100001100000000000 N
b10100 ;
b10111100001100000000000000000000 O
b10111100001100 T
b1000 X
b11101010101001100010101011010101 $
b11101010101001100010101011010101 3
b110101100111111101110101101011 %
b110101100111111101110101101011 4
1"
1)
#42
0"
0)
#43
1G
0B
b11111001000 L
0A
b1111110010000000000000 M
b11111100100 D
0H
b101100 F
b1010 K
b11001000000000 N
b10101 ;
b11010111010101100011111010101110 %
b11010111010101100011111010101110 4
b10000001000101110100101000000010 $
b10000001000101110100101000000010 3
b1001 X
b1011000011001000000000000000000 O
b1011000011001 T
1"
1)
#44
0"
0)
#45
0&
0'
bx0 L
0+
xH
xG
bx00000000000 M
bx D
bx E
bx F
bx K
xI
0C
b110010 0
b110010 R
b1011 /
b1011 Q
b110010000000000 N
b10110 ;
0V
1.
1U
b10110000110010000000000000000000 O
b10110000110010 T
b1010 X
b11100111110001010111001011001111 $
b11100111110001010111001011001111 3
b1110111111111110100100011101 %
b1110111111111110100100011101 4
1"
1)
#46
0"
0)
#47
bx 0
bx R
bx /
bx Q
x+
0.
0U
b10111 ;
15
06
b101000010010110010100001010 %
b101000010010110010100001010 4
b10001100001000100100100100011 $
b10001100001000100100100100011 3
1"
1)
#48
0"
0)
#49
05
b11000 ;
b10011110001100010100110000111100 $
b10011110001100010100110000111100 3
b11100101011100110000101011001010 %
b11100101011100110000101011001010 4
1"
1)
