chapter_10/tut10_1.v

`timescale	1ns / 1ns
`default_nettype none


/*Produced by NSL Core(version=20250428), IP ARCH, Inc. Sun Apr 19 17:47:49 2026
 Licensed to :EVALUATION USER*/
/*
 DO NOT USE ANY PART OF THIS FILE FOR COMMERCIAL PRODUCTS. 
*/

module divu_10_8 ( p_reset , m_clock , A , B , Q , R , divu_do , divu_done , divu_error );
  input p_reset, m_clock;
  wire p_reset, m_clock;
  input [9:0] A;
  wire [9:0] A;
  input [7:0] B;
  wire [7:0] B;
  output [9:0] Q;
  wire [9:0] Q;
  output [7:0] R;
  wire [7:0] R;
  input divu_do;
  wire divu_do;
  output divu_done;
  wire divu_done;
  output divu_error;
  wire divu_error;
  reg [7:0] QB;
  reg [17:0] QQ;
  wire [10:0] sub_i1;
  wire [9:0] sub_i2;
  wire minus;
  wire sub;
  wire [10:0] sub_o;
  reg [7:0] bitcount;
  wire [7:0] _net_2;
  wire _net_3;
  reg _reg_4;
  reg _reg_5;
  reg _reg_6;
  wire _net_7;
  wire _reg_5_goto;
  wire _reg_4_goin;
  wire _net_8;
  wire _reg_5_goin;
  wire [7:0] _net_9;
  wire [19:0] _net_10;
  wire [35:0] _net_11;
  wire [17:0] _net_12;
  wire [21:0] _net_13;
  wire [10:0] _net_14;
  wire _net_15;

   assign  sub_i1 = 
// synthesis translate_off
// synopsys translate_off
((_reg_5&(~_net_7)))? 
// synthesis translate_on
// synopsys translate_on
(((_reg_5&(~_net_7)))?(QQ[17:7]):11'b0)
// synthesis translate_off
// synopsys translate_off
:11'bx
// synthesis translate_on
// synopsys translate_on
;
   assign  sub_i2 = 
// synthesis translate_off
// synopsys translate_off
((_reg_5&(~_net_7)))? 
// synthesis translate_on
// synopsys translate_on
(((_reg_5&(~_net_7)))?(_net_10[17:8]):10'b0)
// synthesis translate_off
// synopsys translate_off
:10'bx
// synthesis translate_on
// synopsys translate_on
;
   assign  minus = 
// synthesis translate_off
// synopsys translate_off
(sub)? 
// synthesis translate_on
// synopsys translate_on
((sub)?(sub_o[10]):1'b0)
// synthesis translate_off
// synopsys translate_off
:1'bx
// synthesis translate_on
// synopsys translate_on
;

// synthesis translate_off
// synopsys translate_off
always @(posedge sub)
  begin
#1 if (sub===1'bx)
 begin
$display("Warning: control hazard(divu_10_8:sub) at %d",$time);
 end
#1 if ((((_reg_5&(~_net_7)))===1'bx) || (1'b1)===1'bx) $display("hazard ((_reg_5&(~_net_7)) || 1'b1) line 37 at %d\n",$time);
 end

// synthesis translate_on
// synopsys translate_on
   assign  sub = (_reg_5&(~_net_7));
   assign  sub_o = 
// synthesis translate_off
// synopsys translate_off
(sub)? 
// synthesis translate_on
// synopsys translate_on
((sub)?(({sub_i1})-({1'b0,sub_i2})):11'b0)
// synthesis translate_off
// synopsys translate_off
:11'bx
// synthesis translate_on
// synopsys translate_on
;
   assign  _net_2 = 
// synthesis translate_off
// synopsys translate_off
((_reg_5&(~_net_7)))? 
// synthesis translate_on
// synopsys translate_on
(((_reg_5&(~_net_7)))?(bitcount+8'b00000001):8'b0)
// synthesis translate_off
// synopsys translate_off
:8'bx
// synthesis translate_on
// synopsys translate_on
;
   assign  _net_3 = 
// synthesis translate_off
// synopsys translate_off
(divu_do)? 
// synthesis translate_on
// synopsys translate_on
((divu_do)?(B==8'b00000000):1'b0)
// synthesis translate_off
// synopsys translate_off
:1'bx
// synthesis translate_on
// synopsys translate_on
;
   assign  _net_7 = 
// synthesis translate_off
// synopsys translate_off
(_reg_5)? 
// synthesis translate_on
// synopsys translate_on
((_reg_5)?(~(bitcount < 8'b00001010)):1'b0)
// synthesis translate_off
// synopsys translate_off
:1'bx
// synthesis translate_on
// synopsys translate_on
;

// synthesis translate_off
// synopsys translate_off
always @(posedge _reg_5_goto)
  begin
#1 if (_reg_5_goto===1'bx)
 begin
$display("Warning: control hazard(divu_10_8:_reg_5_goto) at %d",$time);
 end
#1 if (((((_reg_5&(~_net_7))&_net_8))===1'bx) || (1'b1)===1'bx) $display("hazard (((_reg_5&(~_net_7))&_net_8) || 1'b1) line 43 at %d\n",$time);
#1 if ((((_reg_5&_net_7))===1'bx) || (1'b1)===1'bx) $display("hazard ((_reg_5&_net_7) || 1'b1) line 43 at %d\n",$time);
 end

// synthesis translate_on
// synopsys translate_on
   assign  _reg_5_goto = ((_reg_5&(~_net_7))&_net_8)|
    (_reg_5&_net_7);

// synthesis translate_off
// synopsys translate_off
always @(posedge _reg_4_goin)
  begin
#1 if (_reg_4_goin===1'bx)
 begin
$display("Warning: control hazard(divu_10_8:_reg_4_goin) at %d",$time);
 end
#1 if ((((_reg_5&_net_7))===1'bx) || (1'b1)===1'bx) $display("hazard ((_reg_5&_net_7) || 1'b1) line 43 at %d\n",$time);
 end

// synthesis translate_on
// synopsys translate_on
   assign  _reg_4_goin = (_reg_5&_net_7);
   assign  _net_8 = 
// synthesis translate_off
// synopsys translate_off
((_reg_5&(~_net_7)))? 
// synthesis translate_on
// synopsys translate_on
(((_reg_5&(~_net_7)))?(_net_2 < 8'b00001010):1'b0)
// synthesis translate_off
// synopsys translate_off
:1'bx
// synthesis translate_on
// synopsys translate_on
;

// synthesis translate_off
// synopsys translate_off
always @(posedge _reg_5_goin)
  begin
#1 if (_reg_5_goin===1'bx)
 begin
$display("Warning: control hazard(divu_10_8:_reg_5_goin) at %d",$time);
 end
#1 if (((((_reg_5&(~_net_7))&_net_8))===1'bx) || (1'b1)===1'bx) $display("hazard (((_reg_5&(~_net_7))&_net_8) || 1'b1) line 43 at %d\n",$time);
 end

// synthesis translate_on
// synopsys translate_on
   assign  _reg_5_goin = ((_reg_5&(~_net_7))&_net_8);
   assign  _net_9 = QB;
   assign  _net_10 = ({({2'b00,_net_9}),10'b0000000000});
   assign  _net_11 = ({QQ,18'b000000000000000000});
   assign  _net_12 = ({(QQ[8:0]),9'b000000000});
   assign  _net_13 = ({sub_o,11'b00000000000});
   assign  _net_14 = (_net_13[20:10]);
   assign  _net_15 = 1'b1;
   assign  Q = 
// synthesis translate_off
// synopsys translate_off
(_reg_4)? 
// synthesis translate_on
// synopsys translate_on
((_reg_4)?(QQ[9:0]):10'b0)
// synthesis translate_off
// synopsys translate_off
:10'bx
// synthesis translate_on
// synopsys translate_on
;
   assign  R = 
// synthesis translate_off
// synopsys translate_off
(_reg_4)? 
// synthesis translate_on
// synopsys translate_on
((_reg_4)?(QQ[17:10]):8'b0)
// synthesis translate_off
// synopsys translate_off
:8'bx
// synthesis translate_on
// synopsys translate_on
;

// synthesis translate_off
// synopsys translate_off
always @(posedge divu_done)
  begin
#1 if (divu_done===1'bx)
 begin
$display("Warning: control hazard(divu_10_8:divu_done) at %d",$time);
 end
#1 if (((_reg_4)===1'bx) || (1'b1)===1'bx) $display("hazard (_reg_4 || 1'b1) line 45 at %d\n",$time);
 end

// synthesis translate_on
// synopsys translate_on
   assign  divu_done = _reg_4;

// synthesis translate_off
// synopsys translate_off
always @(posedge divu_error)
  begin
#1 if (divu_error===1'bx)
 begin
$display("Warning: control hazard(divu_10_8:divu_error) at %d",$time);
 end
#1 if ((((divu_do&_net_3))===1'bx) || (1'b1)===1'bx) $display("hazard ((divu_do&_net_3) || 1'b1) line 29 at %d\n",$time);
 end

// synthesis translate_on
// synopsys translate_on
   assign  divu_error = (divu_do&_net_3);
always @(posedge m_clock)
  begin
if (((divu_do&(~_net_3))|_reg_6))
      QB <= B;
end
always @(posedge m_clock)
  begin

// synthesis translate_off
// synopsys translate_off
if (((((divu_do&(~_net_3))|_reg_6)&((_reg_5&(~_net_7))&(~(minus != 1'b0))))|((((divu_do&(~_net_3))|_reg_6)|((_reg_5&(~_net_7))&(~(minus != 1'b0))))&((_reg_5&(~_net_7))&(minus != 1'b0)))))   QQ <= 18'bx; 
  else 
// synthesis translate_on
// synopsys translate_on
if (((divu_do&(~_net_3))|_reg_6))
      QQ <= ({8'b00000000,A});
else if (((_reg_5&(~_net_7))&(~(minus != 1'b0))))
      QQ <= (({(_net_14[10:2]),(_net_12[16:8])})|({17'b00000000000000000,_net_15}));
else if (((_reg_5&(~_net_7))&(minus != 1'b0)))
      QQ <= (_net_11[34:17]);
end

// synthesis translate_off
// synopsys translate_off
always @(posedge m_clock)
  begin
if ((((((divu_do&(~_net_3))|_reg_6)|((_reg_5&(~_net_7))&(~(minus != 1'b0))))|((_reg_5&(~_net_7))&(minus != 1'b0)))==1'b1) ||
 (((((divu_do&(~_net_3))|_reg_6)|((_reg_5&(~_net_7))&(~(minus != 1'b0))))|((_reg_5&(~_net_7))&(minus != 1'b0)))==1'b0) ) begin
 if (((((divu_do&(~_net_3))|_reg_6)&((_reg_5&(~_net_7))&(~(minus != 1'b0))))|((((divu_do&(~_net_3))|_reg_6)|((_reg_5&(~_net_7))&(~(minus != 1'b0))))&((_reg_5&(~_net_7))&(minus != 1'b0)))))
 begin $display("Warning: assign collision(divu_10_8:QQ) at %d",$time);

  end
 end
 else 
 $display("Warning: register set hazard(divu_10_8:QQ) at %d",$time);

  end

// synthesis translate_on
// synopsys translate_on
always @(posedge m_clock)
  begin

// synthesis translate_off
// synopsys translate_off
if ((((divu_do&(~_net_3))|_reg_6)&(_reg_5&(~_net_7))))   bitcount <= 8'bx; 
  else 
// synthesis translate_on
// synopsys translate_on
if (((divu_do&(~_net_3))|_reg_6))
      bitcount <= 8'b00000000;
else if ((_reg_5&(~_net_7)))
      bitcount <= _net_2;
end

// synthesis translate_off
// synopsys translate_off
always @(posedge m_clock)
  begin
if (((((divu_do&(~_net_3))|_reg_6)|(_reg_5&(~_net_7)))==1'b1) ||
 ((((divu_do&(~_net_3))|_reg_6)|(_reg_5&(~_net_7)))==1'b0) ) begin
 if ((((divu_do&(~_net_3))|_reg_6)&(_reg_5&(~_net_7))))
 begin $display("Warning: assign collision(divu_10_8:bitcount) at %d",$time);

  end
 end
 else 
 $display("Warning: register set hazard(divu_10_8:bitcount) at %d",$time);

  end

// synthesis translate_on
// synopsys translate_on
always @(posedge m_clock or posedge p_reset)
  begin
if (p_reset)
     _reg_4 <= 1'b0;
else if (((_reg_5&_net_7)|(_reg_4|_reg_5)))
      _reg_4 <= ((_reg_5&_net_7)|(_reg_5&(~_reg_5_goto)));
end
always @(posedge m_clock or posedge p_reset)
  begin
if (p_reset)
     _reg_5 <= 1'b0;
else if (((((_reg_5&(~_net_7))&_net_8)|(divu_do&(~_net_3)))|(_reg_5|_reg_6)))
      _reg_5 <= ((((_reg_5&(~_net_7))&_net_8)|_reg_6)|(divu_do&(~_net_3)));
end
always @(posedge m_clock or posedge p_reset)
  begin
if (p_reset)
     _reg_6 <= 1'b0;
else if (_reg_6)
      _reg_6 <= 1'b0;
end
endmodule

/*Produced by NSL Core(version=20250428), IP ARCH, Inc. Sun Apr 19 17:47:49 2026
 Licensed to :EVALUATION USER*/

/*Produced by NSL Core(version=20250428), IP ARCH, Inc. Sun Apr 19 17:47:49 2026
 Licensed to :EVALUATION USER*/

// synthesis translate_off
// synopsys translate_off
/*
 DO NOT USE ANY PART OF THIS FILE FOR COMMERCIAL PRODUCTS. 
*/

module tut10_1 ( p_reset , m_clock );
  input p_reset, m_clock;
  wire p_reset, m_clock;
  reg [9:0] a;
  reg [7:0] b;
  wire go;
  reg [15:0] count;
  reg [31:0] _reg_16;
  reg [31:0] _reg_17;
  wire [9:0] _divid_A;
  wire [7:0] _divid_B;
  wire [9:0] _divid_Q;
  wire [7:0] _divid_R;
  wire _divid_divu_do;
  wire _divid_divu_done;
  wire _divid_divu_error;
  wire _divid_p_reset;
  wire _divid_m_clock;
  wire _net_18;
  reg _reg_21;
  reg _reg_22;
  wire [31:0] _net_24;
  wire [31:0] _net_25;
  reg _reg_26;
divu_10_8 divid (.m_clock(m_clock), .p_reset( p_reset), .divu_error(_divid_divu_error), .divu_done(_divid_divu_done), .divu_do(_divid_divu_do), .Q(_divid_Q), .R(_divid_R), .A(_divid_A), .B(_divid_B));

always @(posedge go)
  begin
#1 if (go===1'bx)
 begin
$display("Warning: control hazard(tut10_1:go) at %d",$time);
 end
#1 if (((_net_18)===1'bx) || (1'b1)===1'bx) $display("hazard (_net_18 || 1'b1) line 61 at %d\n",$time);
 end
   assign  go = _net_18;
   assign  _divid_A = (_reg_21)? ((_reg_21)?a:10'b0):10'bx;
   assign  _divid_B = (_reg_21)? ((_reg_21)?b:8'b0):8'bx;
always @(posedge _divid_divu_do)
  begin
#1 if (_divid_divu_do===1'bx)
 begin
$display("Warning: control hazard(tut10_1:_divid_divu_do) at %d",$time);
 end
#1 if (((_reg_21)===1'bx) || (1'b1)===1'bx) $display("hazard (_reg_21 || 1'b1) line 72 at %d\n",$time);
 end
   assign  _divid_divu_do = _reg_21;
   assign  _divid_p_reset = p_reset;
   assign  _divid_m_clock = m_clock;
   assign  _net_18 = (count==16'b0000000000001010);
always @(posedge m_clock)
  begin
    if((_divid_divu_error != 1'b0))
    begin
    $display("divid error");
    end
  end
always @(posedge m_clock)
  begin
    if((_divid_divu_error != 1'b0))
    begin
    $finish;
    end
  end
always @(posedge m_clock)
  begin
    if(_reg_21)
    begin
    $display("start %d/%d",a,b);
    end
  end
   assign  _net_24 = _reg_16;
   assign  _net_25 = _reg_17;
always @(posedge m_clock)
  begin
    if((_divid_divu_done|_reg_26))
    begin
    $finish;
    end
  end
always @(posedge m_clock)
  begin
if ((go|_reg_22))
      a <= (_net_24[9:0]);
end
always @(posedge m_clock)
  begin
if ((go|_reg_22))
      b <= (_net_25[7:0]);
end
always @(posedge m_clock or posedge p_reset)
  begin
if (p_reset)
     count <= 16'b0000000000000000;
else   count <= (count+16'b0000000000000001);
end
always @(posedge m_clock)
  begin
  _reg_16 <= ($random);
end
always @(posedge m_clock)
  begin
  _reg_17 <= ($random);
end
always @(posedge m_clock or posedge p_reset)
  begin
if (p_reset)
     _reg_21 <= 1'b0;
else if ((go|(_reg_21|_reg_22)))
      _reg_21 <= (_reg_22|go);
end
always @(posedge m_clock or posedge p_reset)
  begin
if (p_reset)
     _reg_22 <= 1'b0;
else if (_reg_22)
      _reg_22 <= 1'b0;
end
always @(posedge m_clock or posedge p_reset)
  begin
if (p_reset)
     _reg_26 <= 1'b0;
else if (_reg_26)
      _reg_26 <= 1'b0;
end
endmodule

// synthesis translate_on
// synopsys translate_on

/*Produced by NSL Core(version=20250428), IP ARCH, Inc. Sun Apr 19 17:47:49 2026
 Licensed to :EVALUATION USER*/

/*Produced by NSL Core(version=20250428), IP ARCH, Inc. Sun Apr 19 17:47:49 2026
 Licensed to :EVALUATION USER*/

//synthesis translate_off
/*
 DO NOT USE ANY PART OF THIS FILE FOR COMMERCIAL PRODUCTS. 
*/
module tb;
	parameter tCYC=2;
	parameter tPD=(tCYC/10);

	reg p_reset;
	reg m_clock;

	tut10_1 tut10_1_instance(
		.p_reset(p_reset),
		.m_clock(m_clock)
	);

	initial forever #(tCYC/2) m_clock = ~m_clock;

	initial begin
		$dumpfile("tut10_1.vcd");
		$dumpvars(0,tut10_1_instance);
	end

	initial begin
		#(tPD)
			p_reset = 1;
			m_clock = 0;
		#(tCYC)
			p_reset = 0;
	end

endmodule

//synthesis translate_on

chapter_10/tut10_1.vcd
$date
	Sun Apr 19 17:47:59 2026
$end
$version
	Icarus Verilog
$end
$timescale
	1ns
$end
$scope module tb $end
$scope module tut10_1_instance $end
$var wire 1 ! _divid_divu_do $end
$var wire 1 " _divid_m_clock $end
$var wire 1 # _divid_p_reset $end
$var wire 32 $ _net_24 [31:0] $end
$var wire 32 % _net_25 [31:0] $end
$var wire 1 & go $end
$var wire 1 ' m_clock $end
$var wire 1 ( p_reset $end
$var wire 1 ) _net_18 $end
$var wire 1 * _divid_divu_error $end
$var wire 1 + _divid_divu_done $end
$var wire 8 , _divid_R [7:0] $end
$var wire 10 - _divid_Q [9:0] $end
$var wire 8 . _divid_B [7:0] $end
$var wire 10 / _divid_A [9:0] $end
$var reg 32 0 _reg_16 [31:0] $end
$var reg 32 1 _reg_17 [31:0] $end
$var reg 1 2 _reg_21 $end
$var reg 1 3 _reg_22 $end
$var reg 1 4 _reg_26 $end
$var reg 10 5 a [9:0] $end
$var reg 8 6 b [7:0] $end
$var reg 16 7 count [15:0] $end
$scope module divid $end
$var wire 10 8 A [9:0] $end
$var wire 8 9 B [7:0] $end
$var wire 1 : _net_15 $end
$var wire 8 ; _net_9 [7:0] $end
$var wire 1 < _reg_4_goin $end
$var wire 1 = _reg_5_goin $end
$var wire 1 > _reg_5_goto $end
$var wire 1 ! divu_do $end
$var wire 1 + divu_done $end
$var wire 1 * divu_error $end
$var wire 1 ' m_clock $end
$var wire 1 ( p_reset $end
$var wire 1 ? sub $end
$var wire 11 @ sub_o [10:0] $end
$var wire 10 A sub_i2 [9:0] $end
$var wire 11 B sub_i1 [10:0] $end
$var wire 1 C minus $end
$var wire 1 D _net_8 $end
$var wire 1 E _net_7 $end
$var wire 1 F _net_3 $end
$var wire 8 G _net_2 [7:0] $end
$var wire 11 H _net_14 [10:0] $end
$var wire 22 I _net_13 [21:0] $end
$var wire 18 J _net_12 [17:0] $end
$var wire 36 K _net_11 [35:0] $end
$var wire 20 L _net_10 [19:0] $end
$var wire 8 M R [7:0] $end
$var wire 10 N Q [9:0] $end
$var reg 8 O QB [7:0] $end
$var reg 18 P QQ [17:0] $end
$var reg 1 Q _reg_4 $end
$var reg 1 R _reg_5 $end
$var reg 1 S _reg_6 $end
$var reg 8 T bitcount [7:0] $end
$upscope $end
$upscope $end
$upscope $end
$enddefinitions $end
#0
$dumpvars
bx T
0S
0R
0Q
bx P
bx O
bx N
bx M
b0xxxxxxxx0000000000 L
bx000000000000000000 K
bx000000000 J
bx00000000000 I
bx0 H
bx G
xF
xE
xD
xC
bx B
bx A
bx @
0?
0>
0=
0<
bx ;
1:
bx 9
bx 8
b0 7
bx 6
bx 5
04
03
02
bx 1
bx 0
bx /
bx .
bx -
bx ,
0+
0*
0)
1(
0'
0&
bx %
bx $
1#
0"
0!
$end
#1
b11000000100010010101111010000001 $
b11000000100010010101111010000001 0
b10010000101010011010100100100 %
b10010000101010011010100100100 1
1"
1'
#2
0"
0'
0#
0(
#3
b1 7
b10110001111100000101011001100011 %
b10110001111100000101011001100011 1
b10000100100001001101011000001001 $
b10000100100001001101011000001001 0
1"
1'
#4
0"
0'
#5
b10 7
b1000110110111111001100110001101 $
b1000110110111111001100110001101 0
b110101110010111101100001101 %
b110101110010111101100001101 1
1"
1'
#6
0"
0'
#7
b11 7
b10001001001101110101001000010010 %
b10001001001101110101001000010010 1
b10110010110000101000010001100101 $
b10110010110000101000010001100101 0
1"
1'
#8
0"
0'
#9
b100 7
b110110101111100110100001101 $
b110110101111100110100001101 0
b111100111110001100000001 %
b111100111110001100000001 1
1"
1'
#10
0"
0'
#11
b101 7
b11110100011011100110100111101 %
b11110100011011100110100111101 1
b111011001000111111000101110110 $
b111011001000111111000101110110 0
1"
1'
#12
0"
0'
#13
b110 7
b1000110001011011111011110001100 $
b1000110001011011111011110001100 0
b1110110110101000101011111101101 %
b1110110110101000101011111101101 1
1"
1'
#14
0"
0'
#15
b111 7
b11100011001101110010010011000110 %
b11100011001101110010010011000110 1
b1111100111111011110100111111001 $
b1111100111111011110100111111001 0
1"
1'
#16
0"
0'
#17
b1000 7
b11010101000100111101001010101010 $
b11010101000100111101001010101010 0
b11100010111101111000010011000101 %
b11100010111101111000010011000101 1
1"
1'
#18
0"
0'
#19
b1001 7
b10111011110100100111001001110111 %
b10111011110100100111001001110111 1
b1110010101011111111011111100101 $
b1110010101011111111011111100101 0
1"
1'
#20
0"
0'
#21
1&
1)
b1010 7
b1000111111011001101101110001111 $
b1000111111011001101101110001111 0
b10001001001100101101011000010010 %
b10001001001100101101011000010010 1
1"
1'
#22
0"
0'
#23
0*
b1110001111 /
b1110001111 8
b10010 .
b10010 9
0F
0&
0)
b1011 7
1!
12
b11100111011101101001011011001110 %
b11100111011101101001011011001110 1
b1111001001100000110100111110010 $
b1111001001100000110100111110010 0
b10010 6
b1110001111 5
1"
1'
#24
0"
0'
#25
1C
b11101111110 H
1D
b1111011111100000000000 I
b11110111111 @
b1 G
b1001000 A
b111 B
1=
1>
bx /
bx 8
bx .
bx 9
xF
0E
0<
1?
b110001111000000000 J
0!
02
b1100 7
1R
b100100000000000 L
b10010 ;
b10010 O
b1110001111000000000000000000 K
b1110001111 P
b0 T
b11100010110010100100111011000101 $
b11100010110010100100111011000101 0
b11110100000000000111101011101000 %
b11110100000000000111101011101000 1
1"
1'
#26
0"
0'
#27
b11110001100 H
b1111100011000000000000 I
b11111000110 @
b1110 B
b10 G
b100011110000000000 J
b1101 7
b11011110100011100010100010111101 %
b11011110100011100010100010111101 1
b101110010110000100100101011100 $
b101110010110000100100101011100 0
b1 T
b11100011110000000000000000000 K
b11100011110 P
1"
1'
#28
0"
0'
#29
b11110101000 H
b1111101010000000000000 I
b11111010100 @
b11100 B
b11 G
b111100000000000 J
b1110 7
b111000111100000000000000000000 K
b111000111100 P
b10 T
b10110010101001110010011001100101 $
b10110010101001110010011001100101 0
b10010110101010110101100000101101 %
b10010110101010110101100000101101 1
1"
1'
#30
0"
0'
#31
b11111100000 H
b1111111000000000000000 I
b11111110000 @
b111000 B
b100 G
b1111000000000000 J
b1111 7
b101011100111000011100001010 %
b101011100111000011100001010 1
b10110001111011110110001001100011 $
b10110001111011110110001001100011 0
b11 T
b1110001111000000000000000000000 K
b1110001111000 P
1"
1'
#32
0"
0'
#33
0C
b1010010 H
b10100100000000000 I
b101001 @
b1110001 B
b101 G
b11110000000000000 J
b10000 7
b11100011110000000000000000000000 K
b11100011110000 P
b100 T
b10000011001000010000100100000 $
b10000011001000010000100100000 0
b11000000001110110010001010000000 %
b11000000001110110010001010000000 1
1"
1'
#34
0"
0'
#35
b10110 H
b101100000000000 I
b1011 @
b1010011 B
b110 G
b111100001000000000 J
b10001 7
b11001110110011001100110010011101 %
b11001110110011001100110010011101 1
b1010101011110000100010110101010 $
b1010101011110000100010110101010 0
b101 T
b10100111100001000000000000000000 K
b10100111100001 P
1"
1'
#36
0"
0'
#37
1C
b11110011110 H
b1111100111100000000000 I
b11111001111 @
b10111 B
b111 G
b111000011000000000 J
b10010 7
b101111000011000000000000000000 K
b101111000011 P
b110 T
b10001001100000111011100000010011 $
b10001001100000111011100000010011 0
b11001011001000000011111010010110 %
b11001011001000000011111010010110 1
1"
1'
#38
0"
0'
#39
b11111001110 H
b1111110011100000000000 I
b11111100111 @
b101111 B
b1000 G
b110000110000000000 J
b10011 7
b10101001101001111101011001010011 %
b10101001101001111101011001010011 1
b10000110101111000011100000001101 $
b10000110101111000011100000001101 0
b111 T
b1011110000110000000000000000000 K
b1011110000110 P
1"
1'
#40
0"
0'
#41
0C
b101100 H
b1011000000000000 I
b10110 @
b1011110 B
b1001 G
b100001100000000000 J
b10100 7
b10111100001100000000000000000000 K
b10111100001100 P
b1000 T
b11101010101001100010101011010101 $
b11101010101001100010101011010101 0
b110101100111111101110101101011 %
b110101100111111101110101101011 1
1"
1'
#42
0"
0'
#43
1C
0>
b11111001000 H
0=
b1111110010000000000000 I
b11111100100 @
0D
b101100 B
b1010 G
b11001000000000 J
b10101 7
b11010111010101100011111010101110 %
b11010111010101100011111010101110 1
b10000001000101110100101000000010 $
b10000001000101110100101000000010 0
b1001 T
b1011000011001000000000000000000 K
b1011000011001 P
1"
1'
#44
0"
0'
#45
bx0 H
xD
xC
bx00000000000 I
bx @
bx A
bx B
bx G
xE
0?
b110010 -
b110010 N
b1011 ,
b1011 M
b110010000000000 J
b10110 7
0R
1+
1Q
b10110000110010000000000000000000 K
b10110000110010 P
b1010 T
b11100111110001010111001011001111 $
b11100111110001010111001011001111 0
b1110111111111110100100011101 %
b1110111111111110100100011101 1
1"
1'
#46
0"
0'
#47
bx -
bx N
bx ,
bx M
0+
0Q
b10111 7
1"
1'
