chapter_08/tut8.v

`timescale	1ns / 1ns
`default_nettype none


/*Produced by NSL Core(version=20250428), IP ARCH, Inc. Fri Apr 17 19:32:46 2026
 Licensed to :EVALUATION USER*/

// synthesis translate_off
// synopsys translate_off
/*
 DO NOT USE ANY PART OF THIS FILE FOR COMMERCIAL PRODUCTS. 
*/

module tut8 ( p_reset , m_clock );
  input p_reset, m_clock;
  wire p_reset, m_clock;
  reg [3:0] _count_lo;
  reg [3:0] _count_hi;
  wire [3:0] _res_lo;
  wire [3:0] _res_hi;
  wire [3:0] _sm_a;
  wire [3:0] _sm_b;
  wire _sm_ci;
  wire [3:0] _sm_q;
  wire _sm_c;
  wire _sm_o;
  wire _sm_ex;
  wire _sm_p_reset;
  wire _sm_m_clock;
  wire [3:0] _sm_1_a;
  wire [3:0] _sm_1_b;
  wire _sm_1_ci;
  wire [3:0] _sm_1_q;
  wire _sm_1_c;
  wire _sm_1_o;
  wire _sm_1_ex;
  wire _sm_1_p_reset;
  wire _sm_1_m_clock;
  wire [7:0] _net_0;
  wire _net_1;
  wire _net_3;
fadd4 sm (.m_clock(m_clock), .p_reset( p_reset), .ex(_sm_ex), .o(_sm_o), .c(_sm_c), .q(_sm_q), .ci(_sm_ci), .b(_sm_b), .a(_sm_a));
fadd4 sm_1 (.m_clock(m_clock), .p_reset( p_reset), .ex(_sm_1_ex), .o(_sm_1_o), .c(_sm_1_c), .q(_sm_1_q), .ci(_sm_1_ci), .b(_sm_1_b), .a(_sm_1_a));

   assign  _res_lo = (_net_1)? ((_net_1)?_sm_q:4'b0):4'bx;
   assign  _res_hi = (_net_1)? ((_net_1)?_sm_1_q:4'b0):4'bx;
   assign  _sm_a = (_net_1)? ((_net_1)?_count_lo:4'b0):4'bx;
   assign  _sm_b = (_net_1)? ((_net_1)?_count_lo:4'b0):4'bx;
   assign  _sm_ci = (_net_1)? ((_net_1)?1'b0:1'b0):1'bx;
always @(posedge _sm_ex)
  begin
#1 if (_sm_ex===1'bx)
 begin
$display("Warning: control hazard(tut8:_sm_ex) at %d",$time);
 end
#1 if (((_net_1)===1'bx) || (1'b1)===1'bx) $display("hazard (_net_1 || 1'b1) line 26 at %d\n",$time);
 end
   assign  _sm_ex = _net_1;
   assign  _sm_p_reset = p_reset;
   assign  _sm_m_clock = m_clock;
   assign  _sm_1_a = (_net_1)? ((_net_1)?_count_hi:4'b0):4'bx;
   assign  _sm_1_b = (_net_1)? ((_net_1)?_count_hi:4'b0):4'bx;
   assign  _sm_1_ci = (_net_1)? ((_net_1)?_sm_c:1'b0):1'bx;
always @(posedge _sm_1_ex)
  begin
#1 if (_sm_1_ex===1'bx)
 begin
$display("Warning: control hazard(tut8:_sm_1_ex) at %d",$time);
 end
#1 if (((_net_1)===1'bx) || (1'b1)===1'bx) $display("hazard (_net_1 || 1'b1) line 27 at %d\n",$time);
 end
   assign  _sm_1_ex = _net_1;
   assign  _sm_1_p_reset = p_reset;
   assign  _sm_1_m_clock = m_clock;
   assign  _net_0 = (({_count_hi,_count_lo})+8'b00000001);
   assign  _net_1 = (({_count_hi,_count_lo}) > 8'b00111100);
always @(posedge m_clock)
  begin
    if(_net_1)
    begin
    $display("count:%d, res:%d, ovf:%d",({_count_hi,_count_lo}),({_res_hi,_res_lo}),_sm_1_o);
    end
  end
   assign  _net_3 = (({_count_hi,_count_lo})==8'b01000110);
always @(posedge m_clock)
  begin
    if(_net_3)
    begin
    $display("bye");
    end
  end
always @(posedge m_clock)
  begin
    if(_net_3)
    begin
    $finish;
    end
  end
always @(posedge m_clock or posedge p_reset)
  begin
if (p_reset)
     _count_lo <= 4'b0000;
else   _count_lo <= (_net_0[3:0]);
end
always @(posedge m_clock or posedge p_reset)
  begin
if (p_reset)
     _count_hi <= 4'b0000;
else   _count_hi <= (_net_0[7:4]);
end
endmodule

// synthesis translate_on
// synopsys translate_on

/*Produced by NSL Core(version=20250428), IP ARCH, Inc. Fri Apr 17 19:32:46 2026
 Licensed to :EVALUATION USER*/

/*Produced by NSL Core(version=20250428), IP ARCH, Inc. Fri Apr 17 19:32:46 2026
 Licensed to :EVALUATION USER*/
/*
 DO NOT USE ANY PART OF THIS FILE FOR COMMERCIAL PRODUCTS. 
*/

module fadd4 ( p_reset , m_clock , a , b , ci , q , c , o , ex );
  input p_reset, m_clock;
  wire p_reset, m_clock;
  input [3:0] a;
  wire [3:0] a;
  input [3:0] b;
  wire [3:0] b;
  input ci;
  wire ci;
  output [3:0] q;
  wire [3:0] q;
  output c;
  wire c;
  output o;
  wire o;
  input ex;
  wire ex;
  wire [3:0] qs;
  wire [1:0] qe;
  wire [3:0] _net_6;
  wire [3:0] _net_7;
  wire _net_8;
  wire _net_9;
  wire _net_10;
  wire _net_11;
  wire [3:0] _net_12;

   assign  qs = 
// synthesis translate_off
// synopsys translate_off
(ex)? 
// synthesis translate_on
// synopsys translate_on
((ex)?((({1'b0,(_net_6[2:0])})+({1'b0,(_net_7[2:0])}))+({3'b000,_net_8})):4'b0)
// synthesis translate_off
// synopsys translate_off
:4'bx
// synthesis translate_on
// synopsys translate_on
;
   assign  qe = 
// synthesis translate_off
// synopsys translate_off
(ex)? 
// synthesis translate_on
// synopsys translate_on
((ex)?((({1'b0,_net_9})+({1'b0,_net_10}))+({1'b0,_net_11})):2'b0)
// synthesis translate_off
// synopsys translate_off
:2'bx
// synthesis translate_on
// synopsys translate_on
;
   assign  _net_6 = a;
   assign  _net_7 = b;
   assign  _net_8 = ci;
   assign  _net_9 = (a[3]);
   assign  _net_10 = (b[3]);
   assign  _net_11 = (qs[3]);
   assign  _net_12 = qs;
   assign  q = 
// synthesis translate_off
// synopsys translate_off
(ex)? 
// synthesis translate_on
// synopsys translate_on
((ex)?({(qe[0]),(_net_12[2:0])}):4'b0)
// synthesis translate_off
// synopsys translate_off
:4'bx
// synthesis translate_on
// synopsys translate_on
;
   assign  c = 
// synthesis translate_off
// synopsys translate_off
(ex)? 
// synthesis translate_on
// synopsys translate_on
((ex)?(qe[1]):1'b0)
// synthesis translate_off
// synopsys translate_off
:1'bx
// synthesis translate_on
// synopsys translate_on
;
   assign  o = 
// synthesis translate_off
// synopsys translate_off
(ex)? 
// synthesis translate_on
// synopsys translate_on
((ex)?((qe[1])^(qs[3])):1'b0)
// synthesis translate_off
// synopsys translate_off
:1'bx
// synthesis translate_on
// synopsys translate_on
;
endmodule

/*Produced by NSL Core(version=20250428), IP ARCH, Inc. Fri Apr 17 19:32:46 2026
 Licensed to :EVALUATION USER*/

/*Produced by NSL Core(version=20250428), IP ARCH, Inc. Fri Apr 17 19:32:46 2026
 Licensed to :EVALUATION USER*/

//synthesis translate_off
/*
 DO NOT USE ANY PART OF THIS FILE FOR COMMERCIAL PRODUCTS. 
*/
module tb;
	parameter tCYC=2;
	parameter tPD=(tCYC/10);

	reg p_reset;
	reg m_clock;

	tut8 tut8_instance(
		.p_reset(p_reset),
		.m_clock(m_clock)
	);

	initial forever #(tCYC/2) m_clock = ~m_clock;

	initial begin
		$dumpfile("tut8.vcd");
		$dumpvars(0,tut8_instance);
	end

	initial begin
		#(tPD)
			p_reset = 1;
			m_clock = 0;
		#(tCYC)
			p_reset = 0;
	end

endmodule

//synthesis translate_on

chapter_08/tut8.vcd
$date
	Fri Apr 17 19:45:01 2026
$end
$version
	Icarus Verilog
$end
$timescale
	1ns
$end
$scope module tb $end
$scope module tut8_instance $end
$var wire 1 ! _sm_1_ex $end
$var wire 1 " _sm_1_m_clock $end
$var wire 1 # _sm_1_p_reset $end
$var wire 1 $ _sm_ex $end
$var wire 1 % _sm_m_clock $end
$var wire 1 & _sm_p_reset $end
$var wire 1 ' m_clock $end
$var wire 1 ( p_reset $end
$var wire 4 ) _sm_q [3:0] $end
$var wire 1 * _sm_o $end
$var wire 1 + _sm_ci $end
$var wire 1 , _sm_c $end
$var wire 4 - _sm_b [3:0] $end
$var wire 4 . _sm_a [3:0] $end
$var wire 4 / _sm_1_q [3:0] $end
$var wire 1 0 _sm_1_o $end
$var wire 1 1 _sm_1_ci $end
$var wire 1 2 _sm_1_c $end
$var wire 4 3 _sm_1_b [3:0] $end
$var wire 4 4 _sm_1_a [3:0] $end
$var wire 4 5 _res_lo [3:0] $end
$var wire 4 6 _res_hi [3:0] $end
$var wire 1 7 _net_3 $end
$var wire 1 8 _net_1 $end
$var wire 8 9 _net_0 [7:0] $end
$var reg 4 : _count_hi [3:0] $end
$var reg 4 ; _count_lo [3:0] $end
$scope module sm $end
$var wire 4 < _net_12 [3:0] $end
$var wire 4 = _net_6 [3:0] $end
$var wire 4 > _net_7 [3:0] $end
$var wire 1 ? _net_8 $end
$var wire 4 @ a [3:0] $end
$var wire 4 A b [3:0] $end
$var wire 1 + ci $end
$var wire 1 $ ex $end
$var wire 1 ' m_clock $end
$var wire 1 ( p_reset $end
$var wire 4 B qs [3:0] $end
$var wire 2 C qe [1:0] $end
$var wire 4 D q [3:0] $end
$var wire 1 * o $end
$var wire 1 , c $end
$var wire 1 E _net_9 $end
$var wire 1 F _net_11 $end
$var wire 1 G _net_10 $end
$upscope $end
$scope module sm_1 $end
$var wire 4 H _net_12 [3:0] $end
$var wire 4 I _net_6 [3:0] $end
$var wire 4 J _net_7 [3:0] $end
$var wire 1 K _net_8 $end
$var wire 4 L a [3:0] $end
$var wire 4 M b [3:0] $end
$var wire 1 1 ci $end
$var wire 1 ! ex $end
$var wire 1 ' m_clock $end
$var wire 1 ( p_reset $end
$var wire 4 N qs [3:0] $end
$var wire 2 O qe [1:0] $end
$var wire 4 P q [3:0] $end
$var wire 1 0 o $end
$var wire 1 2 c $end
$var wire 1 Q _net_9 $end
$var wire 1 R _net_11 $end
$var wire 1 S _net_10 $end
$upscope $end
$upscope $end
$upscope $end
$enddefinitions $end
#0
$dumpvars
xS
xR
xQ
bx P
bx O
bx N
bx M
bx L
xK
bx J
bx I
bx H
xG
xF
xE
bx D
bx C
bx B
bx A
bx @
x?
bx >
bx =
bx <
b0 ;
b0 :
b1 9
08
07
bx 6
bx 5
bx 4
bx 3
x2
x1
x0
bx /
bx .
bx -
x,
x+
x*
bx )
1(
0'
1&
0%
0$
1#
0"
0!
$end
#1
1%
1"
1'
#2
0%
0"
0'
0&
0#
0(
#3
b10 9
b1 ;
1%
1"
1'
#4
0%
0"
0'
#5
b11 9
b10 ;
1%
1"
1'
#6
0%
0"
0'
#7
b100 9
b11 ;
1%
1"
1'
#8
0%
0"
0'
#9
b101 9
b100 ;
1%
1"
1'
#10
0%
0"
0'
#11
b110 9
b101 ;
1%
1"
1'
#12
0%
0"
0'
#13
b111 9
b110 ;
1%
1"
1'
#14
0%
0"
0'
#15
b1000 9
b111 ;
1%
1"
1'
#16
0%
0"
0'
#17
b1001 9
b1000 ;
1%
1"
1'
#18
0%
0"
0'
#19
b1010 9
b1001 ;
1%
1"
1'
#20
0%
0"
0'
#21
b1011 9
b1010 ;
1%
1"
1'
#22
0%
0"
0'
#23
b1100 9
b1011 ;
1%
1"
1'
#24
0%
0"
0'
#25
b1101 9
b1100 ;
1%
1"
1'
#26
0%
0"
0'
#27
b1110 9
b1101 ;
1%
1"
1'
#28
0%
0"
0'
#29
b1111 9
b1110 ;
1%
1"
1'
#30
0%
0"
0'
#31
b10000 9
b1111 ;
1%
1"
1'
#32
0%
0"
0'
#33
b1 :
b10001 9
b0 ;
1%
1"
1'
#34
0%
0"
0'
#35
b10010 9
b1 ;
1%
1"
1'
#36
0%
0"
0'
#37
b10011 9
b10 ;
1%
1"
1'
#38
0%
0"
0'
#39
b10100 9
b11 ;
1%
1"
1'
#40
0%
0"
0'
#41
b10101 9
b100 ;
1%
1"
1'
#42
0%
0"
0'
#43
b10110 9
b101 ;
1%
1"
1'
#44
0%
0"
0'
#45
b10111 9
b110 ;
1%
1"
1'
#46
0%
0"
0'
#47
b11000 9
b111 ;
1%
1"
1'
#48
0%
0"
0'
#49
b11001 9
b1000 ;
1%
1"
1'
#50
0%
0"
0'
#51
b11010 9
b1001 ;
1%
1"
1'
#52
0%
0"
0'
#53
b11011 9
b1010 ;
1%
1"
1'
#54
0%
0"
0'
#55
b11100 9
b1011 ;
1%
1"
1'
#56
0%
0"
0'
#57
b11101 9
b1100 ;
1%
1"
1'
#58
0%
0"
0'
#59
b11110 9
b1101 ;
1%
1"
1'
#60
0%
0"
0'
#61
b11111 9
b1110 ;
1%
1"
1'
#62
0%
0"
0'
#63
b100000 9
b1111 ;
1%
1"
1'
#64
0%
0"
0'
#65
b10 :
b100001 9
b0 ;
1%
1"
1'
#66
0%
0"
0'
#67
b100010 9
b1 ;
1%
1"
1'
#68
0%
0"
0'
#69
b100011 9
b10 ;
1%
1"
1'
#70
0%
0"
0'
#71
b100100 9
b11 ;
1%
1"
1'
#72
0%
0"
0'
#73
b100101 9
b100 ;
1%
1"
1'
#74
0%
0"
0'
#75
b100110 9
b101 ;
1%
1"
1'
#76
0%
0"
0'
#77
b100111 9
b110 ;
1%
1"
1'
#78
0%
0"
0'
#79
b101000 9
b111 ;
1%
1"
1'
#80
0%
0"
0'
#81
b101001 9
b1000 ;
1%
1"
1'
#82
0%
0"
0'
#83
b101010 9
b1001 ;
1%
1"
1'
#84
0%
0"
0'
#85
b101011 9
b1010 ;
1%
1"
1'
#86
0%
0"
0'
#87
b101100 9
b1011 ;
1%
1"
1'
#88
0%
0"
0'
#89
b101101 9
b1100 ;
1%
1"
1'
#90
0%
0"
0'
#91
b101110 9
b1101 ;
1%
1"
1'
#92
0%
0"
0'
#93
b101111 9
b1110 ;
1%
1"
1'
#94
0%
0"
0'
#95
b110000 9
b1111 ;
1%
1"
1'
#96
0%
0"
0'
#97
b11 :
b110001 9
b0 ;
1%
1"
1'
#98
0%
0"
0'
#99
b110010 9
b1 ;
1%
1"
1'
#100
0%
0"
0'
#101
b110011 9
b10 ;
1%
1"
1'
#102
0%
0"
0'
#103
b110100 9
b11 ;
1%
1"
1'
#104
0%
0"
0'
#105
b110101 9
b100 ;
1%
1"
1'
#106
0%
0"
0'
#107
b110110 9
b101 ;
1%
1"
1'
#108
0%
0"
0'
#109
b110111 9
b110 ;
1%
1"
1'
#110
0%
0"
0'
#111
b111000 9
b111 ;
1%
1"
1'
#112
0%
0"
0'
#113
b111001 9
b1000 ;
1%
1"
1'
#114
0%
0"
0'
#115
b111010 9
b1001 ;
1%
1"
1'
#116
0%
0"
0'
#117
b111011 9
b1010 ;
1%
1"
1'
#118
0%
0"
0'
#119
b111100 9
b1011 ;
1%
1"
1'
#120
0%
0"
0'
#121
b111101 9
b1100 ;
1%
1"
1'
#122
0%
0"
0'
#123
0S
0Q
1G
1E
0R
1F
1K
11
b11 J
b11 3
b11 M
b11 I
b11 4
b11 L
0?
0+
b1101 >
b1101 -
b1101 A
b1101 =
b1101 .
b1101 @
b111 6
b1010 5
b111 H
b111 N
b0 O
b111 /
b111 P
02
00
b1010 <
b1010 B
b11 C
b1010 )
b1010 D
1,
0*
b111110 9
1!
1$
18
b1101 ;
1%
1"
1'
#124
0%
0"
0'
#125
b1100 5
b1100 )
b1100 D
b1100 <
b1100 B
b1110 =
b1110 .
b1110 @
b1110 >
b1110 -
b1110 A
b111111 9
b1110 ;
1%
1"
1'
#126
0%
0"
0'
#127
b1110 5
b1110 )
b1110 D
b1110 <
b1110 B
b1111 =
b1111 .
b1111 @
b1111 >
b1111 -
b1111 A
b1000000 9
b1111 ;
1%
1"
1'
#128
0%
0"
0'
#129
b1000 6
b0 5
0K
01
10
b1 O
b1000 /
b1000 P
b0 )
b0 D
0,
1R
0F
b1000 H
b1000 N
b0 <
b0 B
b0 C
0G
0E
b100 J
b100 3
b100 M
b100 I
b100 4
b100 L
b0 >
b0 -
b0 A
b0 =
b0 .
b0 @
b100 :
b1000001 9
1!
1$
18
b0 ;
1%
1"
1'
#130
0%
0"
0'
#131
b10 5
b10 )
b10 D
b10 <
b10 B
b1 =
b1 .
b1 @
b1 >
b1 -
b1 A
b1000010 9
b1 ;
1%
1"
1'
#132
0%
0"
0'
#133
b100 5
b100 )
b100 D
b100 <
b100 B
b10 =
b10 .
b10 @
b10 >
b10 -
b10 A
b1000011 9
b10 ;
1%
1"
1'
#134
0%
0"
0'
#135
b110 5
b110 )
b110 D
b110 <
b110 B
b11 =
b11 .
b11 @
b11 >
b11 -
b11 A
b1000100 9
b11 ;
1%
1"
1'
#136
0%
0"
0'
#137
b1000 5
1*
b1 C
b1000 )
b1000 D
1F
b1000 <
b1000 B
b100 =
b100 .
b100 @
b100 >
b100 -
b100 A
b1000101 9
b100 ;
1%
1"
1'
#138
0%
0"
0'
#139
b1010 5
b1010 )
b1010 D
b1010 <
b1010 B
b101 =
b101 .
b101 @
b101 >
b101 -
b101 A
b1000110 9
b101 ;
1%
1"
1'
#140
0%
0"
0'
#141
b1100 5
b1100 )
b1100 D
b1100 <
b1100 B
b110 =
b110 .
b110 @
b110 >
b110 -
b110 A
b1000111 9
17
b110 ;
1%
1"
1'
#142
0%
0"
0'
#143
b1110 5
b1110 )
b1110 D
b1110 <
b1110 B
b111 =
b111 .
b111 @
b111 >
b111 -
b111 A
b1001000 9
07
b111 ;
1%
1"
1'
