chapter_07/tut7.v

`timescale	1ns / 1ns
`default_nettype none


/*Produced by NSL Core(version=20250428), IP ARCH, Inc. Fri Apr 17 18:45:03 2026
 Licensed to :EVALUATION USER*/

// synthesis translate_off
// synopsys translate_off
/*
 DO NOT USE ANY PART OF THIS FILE FOR COMMERCIAL PRODUCTS. 
*/

module tut7 ( p_reset , m_clock );
  input p_reset, m_clock;
  wire p_reset, m_clock;
  reg [7:0] count;
  wire [7:0] value;
  wire start;
  wire _net_0;
  reg _reg_1;
  reg _reg_2;
  reg _reg_3;
  reg _reg_4;

   assign  value = (_net_0)? ((_net_0)?count:8'b0):8'bx;
always @(posedge start)
  begin
#1 if (start===1'bx)
 begin
$display("Warning: control hazard(tut7:start) at %d",$time);
 end
#1 if (((_net_0)===1'bx) || (1'b1)===1'bx) $display("hazard (_net_0 || 1'b1) line 9 at %d\n",$time);
 end
   assign  start = _net_0;
   assign  _net_0 = (count==8'b01100100);
always @(posedge m_clock)
  begin
    if(_reg_1)
    begin
    $display("bye: count = %d",count);
    end
  end
always @(posedge m_clock)
  begin
    if(_reg_1)
    begin
    $finish;
    end
  end
always @(posedge m_clock)
  begin
    if(_reg_2)
    begin
    $display("count = %d",count);
    end
  end
always @(posedge m_clock)
  begin
    if(_reg_3)
    begin
    $display("count = %d",count);
    end
  end
always @(posedge m_clock)
  begin
    if((start|_reg_4))
    begin
    $display("Hello World: value = %d, count = %d",value,count);
    end
  end
always @(posedge m_clock or posedge p_reset)
  begin
if (p_reset)
     count <= 8'b00000000;
else   count <= (count+8'b00000001);
end
always @(posedge m_clock or posedge p_reset)
  begin
if (p_reset)
     _reg_1 <= 1'b0;
else if ((_reg_1|_reg_2))
      _reg_1 <= _reg_2;
end
always @(posedge m_clock or posedge p_reset)
  begin
if (p_reset)
     _reg_2 <= 1'b0;
else if ((_reg_2|_reg_3))
      _reg_2 <= _reg_3;
end
always @(posedge m_clock or posedge p_reset)
  begin
if (p_reset)
     _reg_3 <= 1'b0;
else if ((start|(_reg_3|_reg_4)))
      _reg_3 <= (_reg_4|start);
end
always @(posedge m_clock or posedge p_reset)
  begin
if (p_reset)
     _reg_4 <= 1'b0;
else if (_reg_4)
      _reg_4 <= 1'b0;
end
endmodule

// synthesis translate_on
// synopsys translate_on

/*Produced by NSL Core(version=20250428), IP ARCH, Inc. Fri Apr 17 18:45:03 2026
 Licensed to :EVALUATION USER*/

/*Produced by NSL Core(version=20250428), IP ARCH, Inc. Fri Apr 17 18:45:03 2026
 Licensed to :EVALUATION USER*/

//synthesis translate_off
/*
 DO NOT USE ANY PART OF THIS FILE FOR COMMERCIAL PRODUCTS. 
*/
module tb;
	parameter tCYC=2;
	parameter tPD=(tCYC/10);

	reg p_reset;
	reg m_clock;

	tut7 tut7_instance(
		.p_reset(p_reset),
		.m_clock(m_clock)
	);

	initial forever #(tCYC/2) m_clock = ~m_clock;

	initial begin
		$dumpfile("tut7.vcd");
		$dumpvars(0,tut7_instance);
	end

	initial begin
		#(tPD)
			p_reset = 1;
			m_clock = 0;
		#(tCYC)
			p_reset = 0;
	end

endmodule

//synthesis translate_on

chapter_07/tut7.vcd
$date
	Mon Apr 20 15:44:50 2026
$end
$version
	Icarus Verilog
$end
$timescale
	1ns
$end
$scope module tb $end
$scope module tut7_instance $end
$var wire 1 ! m_clock $end
$var wire 1 " p_reset $end
$var wire 1 # start $end
$var wire 8 $ value [7:0] $end
$var wire 1 % _net_0 $end
$var reg 1 & _reg_1 $end
$var reg 1 ' _reg_2 $end
$var reg 1 ( _reg_3 $end
$var reg 1 ) _reg_4 $end
$var reg 8 * count [7:0] $end
$upscope $end
$upscope $end
$enddefinitions $end
#0
$dumpvars
b0 *
0)
0(
0'
0&
0%
bx $
0#
1"
0!
$end
#1
1!
#2
0!
0"
#3
b1 *
1!
#4
0!
#5
b10 *
1!
#6
0!
#7
b11 *
1!
#8
0!
#9
b100 *
1!
#10
0!
#11
b101 *
1!
#12
0!
#13
b110 *
1!
#14
0!
#15
b111 *
1!
#16
0!
#17
b1000 *
1!
#18
0!
#19
b1001 *
1!
#20
0!
#21
b1010 *
1!
#22
0!
#23
b1011 *
1!
#24
0!
#25
b1100 *
1!
#26
0!
#27
b1101 *
1!
#28
0!
#29
b1110 *
1!
#30
0!
#31
b1111 *
1!
#32
0!
#33
b10000 *
1!
#34
0!
#35
b10001 *
1!
#36
0!
#37
b10010 *
1!
#38
0!
#39
b10011 *
1!
#40
0!
#41
b10100 *
1!
#42
0!
#43
b10101 *
1!
#44
0!
#45
b10110 *
1!
#46
0!
#47
b10111 *
1!
#48
0!
#49
b11000 *
1!
#50
0!
#51
b11001 *
1!
#52
0!
#53
b11010 *
1!
#54
0!
#55
b11011 *
1!
#56
0!
#57
b11100 *
1!
#58
0!
#59
b11101 *
1!
#60
0!
#61
b11110 *
1!
#62
0!
#63
b11111 *
1!
#64
0!
#65
b100000 *
1!
#66
0!
#67
b100001 *
1!
#68
0!
#69
b100010 *
1!
#70
0!
#71
b100011 *
1!
#72
0!
#73
b100100 *
1!
#74
0!
#75
b100101 *
1!
#76
0!
#77
b100110 *
1!
#78
0!
#79
b100111 *
1!
#80
0!
#81
b101000 *
1!
#82
0!
#83
b101001 *
1!
#84
0!
#85
b101010 *
1!
#86
0!
#87
b101011 *
1!
#88
0!
#89
b101100 *
1!
#90
0!
#91
b101101 *
1!
#92
0!
#93
b101110 *
1!
#94
0!
#95
b101111 *
1!
#96
0!
#97
b110000 *
1!
#98
0!
#99
b110001 *
1!
#100
0!
#101
b110010 *
1!
#102
0!
#103
b110011 *
1!
#104
0!
#105
b110100 *
1!
#106
0!
#107
b110101 *
1!
#108
0!
#109
b110110 *
1!
#110
0!
#111
b110111 *
1!
#112
0!
#113
b111000 *
1!
#114
0!
#115
b111001 *
1!
#116
0!
#117
b111010 *
1!
#118
0!
#119
b111011 *
1!
#120
0!
#121
b111100 *
1!
#122
0!
#123
b111101 *
1!
#124
0!
#125
b111110 *
1!
#126
0!
#127
b111111 *
1!
#128
0!
#129
b1000000 *
1!
#130
0!
#131
b1000001 *
1!
#132
0!
#133
b1000010 *
1!
#134
0!
#135
b1000011 *
1!
#136
0!
#137
b1000100 *
1!
#138
0!
#139
b1000101 *
1!
#140
0!
#141
b1000110 *
1!
#142
0!
#143
b1000111 *
1!
#144
0!
#145
b1001000 *
1!
#146
0!
#147
b1001001 *
1!
#148
0!
#149
b1001010 *
1!
#150
0!
#151
b1001011 *
1!
#152
0!
#153
b1001100 *
1!
#154
0!
#155
b1001101 *
1!
#156
0!
#157
b1001110 *
1!
#158
0!
#159
b1001111 *
1!
#160
0!
#161
b1010000 *
1!
#162
0!
#163
b1010001 *
1!
#164
0!
#165
b1010010 *
1!
#166
0!
#167
b1010011 *
1!
#168
0!
#169
b1010100 *
1!
#170
0!
#171
b1010101 *
1!
#172
0!
#173
b1010110 *
1!
#174
0!
#175
b1010111 *
1!
#176
0!
#177
b1011000 *
1!
#178
0!
#179
b1011001 *
1!
#180
0!
#181
b1011010 *
1!
#182
0!
#183
b1011011 *
1!
#184
0!
#185
b1011100 *
1!
#186
0!
#187
b1011101 *
1!
#188
0!
#189
b1011110 *
1!
#190
0!
#191
b1011111 *
1!
#192
0!
#193
b1100000 *
1!
#194
0!
#195
b1100001 *
1!
#196
0!
#197
b1100010 *
1!
#198
0!
#199
b1100011 *
1!
#200
0!
#201
b1100100 $
1#
1%
b1100100 *
1!
#202
0!
#203
bx $
0#
0%
b1100101 *
1(
1!
#204
0!
#205
0(
1'
b1100110 *
1!
#206
0!
#207
b1100111 *
1&
0'
1!
#208
0!
#209
0&
b1101000 *
1!
